{"name": "LoRAthens AQ5", "gauges": "", "gauges2": "", "statuses": "", "url": "https://thingspeak.com//channels/326550", "author": "hloupis", "disc": "Air quality station from LoRAthens network - Ilion", "tags": ["LoRAthens","air quality","PM2.5","PM10"], "shares": "0", "charts": ["/channels/326550/charts/1?bgcolor=%23ffffff&color=%23d62020&dynamic=true&results=60&type=line&update=15","/channels/326550/charts/2?bgcolor=%23ffffff&color=%23d62020&dynamic=true&results=60&type=line&update=15","/channels/326550/charts/3?bgcolor=%23ffffff&color=%23d62020&dynamic=true&results=60&type=line&update=15","/channels/326550/maps/channel_show"], "comments": [], "maps": "", "matlabs": "", "language": "en"}