{"name": "MHPV 367985", "gauges": "", "gauges2": "", "statuses": "", "url": "https://thingspeak.com//channels/367985", "author": "mhpv34", "disc": "", "tags": ], "shares": "0", "charts": ["/channels/367985/charts/5?bgcolor=%23ffffff&color=%23d62020&days=1&dynamic=true&type=column&yaxismax=%2B5000&yaxismin=-5000","/channels/367985/charts/1?bgcolor=%23ffffff&color=%23d62020&days=1&dynamic=true&type=column&yaxismax=0&yaxismin=-5000","/channels/367985/charts/2?bgcolor=%23ffffff&color=%23d62020&days=1&dynamic=true&type=column&yaxismax=5000&yaxismin=0","/channels/367985/charts/3?bgcolor=%23ffffff&color=%23d62020&days=1&dynamic=true&type=column&yaxismax=5000&yaxismin=0","/channels/367985/charts/4?bgcolor=%23ffffff&color=%23d62020&days=1&dynamic=true&type=column&yaxismax=5000&yaxismin=0","/channels/367985/charts/6?bgcolor=%23ffffff&color=%23d62020&days=1&dynamic=true&type=column&yaxismax=5000&yaxismin=0","/channels/367985/charts/7?bgcolor=%23ffffff&color=%23d62020&days=1&dynamic=true&type=line","/channels/367985/charts/8?bgcolor=%23ffffff&color=%23d62020&days=1&dynamic=true&type=line","/channels/367985/status/recent"], "comments": [], "maps": "", "matlabs": "", "language": "sk"}