{"name": "Solar hot water system, homemade", "url": "https://thingspeak.com//channels/43709", "author": "szabonandi73", "disc": "Solar hot water system, esp8266 as thingspeak logger from serial CSV data", "tags": ["nandi","Solar","ESP","esp8266","collector","Boiler"], "charts": [{ "title": "Collector Temperature - Google Gauge", "second_title": "", "xaxis": "", "yaxis": "", "chart_type": "", "results": "", "header": "/apps/plugins/58344"},{ "title": "Boiler Temperature - Google Gauge", "second_title": "", "xaxis": "", "yaxis": "", "chart_type": "", "results": "", "header": "/apps/plugins/58346"},{ "title": "Field 2 Chart", "second_title": "Collector temperature, °C", "xaxis": "", "yaxis": "", "chart_type": "line", "results": "", "header": "/channels/43709/charts/2?bgcolor=%23ffffff&color=%23d62020&days=1&dynamic=true&title=Collector+temperature%2C+%C2%B0C&type=line"},{ "title": "Field 1 Chart", "second_title": "Boiler temperature, °C", "xaxis": "", "yaxis": "", "chart_type": "line", "results": "", "header": "/channels/43709/charts/1?bgcolor=%23ffffff&color=%23d62020&days=1&dynamic=true&title=Boiler+temperature%2C+%C2%B0C&type=line"},{ "title": "Field 3 Chart", "second_title": "Pump state, 0-Off, 1-On", "xaxis": "", "yaxis": "", "chart_type": "line", "results": "", "header": "/channels/43709/charts/3?bgcolor=%23ffffff&color=%23d62020&days=1&dynamic=true&title=Pump+state%2C+0-Off%2C+1-On&type=line"},{ "title": "Channel Location", "second_title": "", "xaxis": "", "yaxis": "", "chart_type": "", "results": "", "header": "/channels/43709/maps/channel_show"},{ "title": "Channel Video", "second_title": "", "xaxis": "", "yaxis": "", "chart_type": "", "results": "", "header": "https://www.youtube.com/embed/vJpXUqdeRuE?wmode=transparent"}]}