{"name": "Station", "url": "https://thingspeak.com//channels/494847", "author": "tomank", "disc": "", "tags": ], "charts": [{ "title": "Outdoor temperature", "second_title": "", "xaxis": "", "yaxis": "", "chart_type": "", "results": "", "header": "/channels/494847/widgets/580"},{ "title": "Field 1 Chart", "second_title": "Outdoor temperature (°C)", "xaxis": "Date", "yaxis": "Outdoor temperature (°C)", "chart_type": "spline", "results": "", "header": "/channels/494847/charts/1?bgcolor=%23ffffff&color=%23d62020&days=2&dynamic=true&timescale=60&title=Outdoor+temperature+%28%C2%B0C%29&type=spline&xaxis=Date&yaxis=Outdoor+temperature+%28%C2%B0C%29"},{ "title": "Outdoor humidity", "second_title": "", "xaxis": "", "yaxis": "", "chart_type": "", "results": "", "header": "/channels/494847/widgets/581"},{ "title": "Field 2 Chart", "second_title": "Outdoor humidity (%)", "xaxis": "Date", "yaxis": "Outdoor humidity (%)", "chart_type": "spline", "results": "", "header": "/channels/494847/charts/2?bgcolor=%23ffffff&color=%23d62020&days=2&dynamic=true&timescale=60&title=Outdoor+humidity+%28%25%29&type=spline&xaxis=Date&yaxis=Outdoor+humidity+%28%25%29"},{ "title": "Atmospheric pressure", "second_title": "", "xaxis": "", "yaxis": "", "chart_type": "", "results": "", "header": "/channels/494847/widgets/1537"},{ "title": "Field 5 Chart", "second_title": "Atmospheric pressure (hPa)", "xaxis": "Date", "yaxis": "Atmospheric pressure (hPa)", "chart_type": "spline", "results": "", "header": "/channels/494847/charts/5?bgcolor=%23ffffff&color=%23d62020&days=2&dynamic=true&timescale=60&title=Atmospheric+pressure+%28hPa%29&type=spline&xaxis=Date&yaxis=Atmospheric+pressure+%28hPa%29"},{ "title": "CPU temperature", "second_title": "", "xaxis": "", "yaxis": "", "chart_type": "", "results": "", "header": "/channels/494847/widgets/5154"},{ "title": "Field 6 Chart", "second_title": "CPU temperature (°C)", "xaxis": "Date", "yaxis": "CPU temperature (°C)", "chart_type": "spline", "results": "", "header": "/channels/494847/charts/6?bgcolor=%23ffffff&color=%23d62020&days=2&dynamic=true&timescale=60&title=CPU+temperature+%28%C2%B0C%29&type=spline&xaxis=Date&yaxis=CPU+temperature+%28%C2%B0C%29"},{ "title": "Field 7 Chart", "second_title": "Outdoor temperature (°C) [long term]", "xaxis": "Date", "yaxis": "Outdoor temperature (°C)", "chart_type": "spline", "results": "", "header": "/channels/494847/charts/7?average=daily&bgcolor=%23ffffff&color=%23d62020&days=180&dynamic=true&round=0&title=Outdoor+temperature+%28%C2%B0C%29+%5Blong+term%5D&type=spline&xaxis=Date&yaxis=Outdoor+temperature+%28%C2%B0C%29"}]}{"name": "Station", "url": "https://thingspeak.com//channels/494847", "author": "tomank", "disc": "", "tags": ], "charts": [{ "title": "Outdoor temperature", "second_title": "", "xaxis": "", "yaxis": "", "chart_type": "", "results": "", "header": "/channels/494847/widgets/580"},{ "title": "Field 1 Chart", "second_title": "Outdoor temperature (°C)", "xaxis": "Date", "yaxis": "Outdoor temperature (°C)", "chart_type": "spline", "results": "", "header": "/channels/494847/charts/1?bgcolor=%23ffffff&color=%23d62020&days=2&dynamic=true&timescale=60&title=Outdoor+temperature+%28%C2%B0C%29&type=spline&xaxis=Date&yaxis=Outdoor+temperature+%28%C2%B0C%29"},{ "title": "Outdoor humidity", "second_title": "", "xaxis": "", "yaxis": "", "chart_type": "", "results": "", "header": "/channels/494847/widgets/581"},{ "title": "Field 2 Chart", "second_title": "Outdoor humidity (%)", "xaxis": "Date", "yaxis": "Outdoor humidity (%)", "chart_type": "spline", "results": "", "header": "/channels/494847/charts/2?bgcolor=%23ffffff&color=%23d62020&days=2&dynamic=true&timescale=60&title=Outdoor+humidity+%28%25%29&type=spline&xaxis=Date&yaxis=Outdoor+humidity+%28%25%29"},{ "title": "Atmospheric pressure", "second_title": "", "xaxis": "", "yaxis": "", "chart_type": "", "results": "", "header": "/channels/494847/widgets/1537"},{ "title": "Field 5 Chart", "second_title": "Atmospheric pressure (hPa)", "xaxis": "Date", "yaxis": "Atmospheric pressure (hPa)", "chart_type": "spline", "results": "", "header": "/channels/494847/charts/5?bgcolor=%23ffffff&color=%23d62020&days=2&dynamic=true&timescale=60&title=Atmospheric+pressure+%28hPa%29&type=spline&xaxis=Date&yaxis=Atmospheric+pressure+%28hPa%29"},{ "title": "CPU temperature", "second_title": "", "xaxis": "", "yaxis": "", "chart_type": "", "results": "", "header": "/channels/494847/widgets/5154"},{ "title": "Field 6 Chart", "second_title": "CPU temperature (°C)", "xaxis": "Date", "yaxis": "CPU temperature (°C)", "chart_type": "spline", "results": "", "header": "/channels/494847/charts/6?bgcolor=%23ffffff&color=%23d62020&days=2&dynamic=true&timescale=60&title=CPU+temperature+%28%C2%B0C%29&type=spline&xaxis=Date&yaxis=CPU+temperature+%28%C2%B0C%29"},{ "title": "Field 7 Chart", "second_title": "Outdoor temperature (°C) [long term]", "xaxis": "Date", "yaxis": "Outdoor temperature (°C)", "chart_type": "spline", "results": "", "header": "/channels/494847/charts/7?average=daily&bgcolor=%23ffffff&color=%23d62020&days=180&dynamic=true&round=0&title=Outdoor+temperature+%28%C2%B0C%29+%5Blong+term%5D&type=spline&xaxis=Date&yaxis=Outdoor+temperature+%28%C2%B0C%29"}]}