{"channel":{"id":259502,"name":"Alpua","latitude":"0.0","longitude":"0.0","field1":"VaraajaKeski","field2":"Ulko","field3":"SisäLt","field4":"PatteriMeno","field5":"PatteriPaluu","field6":"VaraajaYlä","field7":"Kylmävesi","field8":"VaraajaAla","created_at":"2017-04-17T10:33:48Z","updated_at":"2018-09-08T23:21:19Z","last_entry_id":245540},"feeds":[{"created_at":"2018-09-14T18:06:18Z","entry_id":245441,"field1":"34.38","field2":"8.19","field3":"23.25","field4":"85.00","field5":"25.25","field6":"51.81","field7":"13.06","field8":"46.38"},{"created_at":"2018-09-14T18:09:20Z","entry_id":245442,"field1":"34.31","field2":"8.12","field3":"23.25","field4":"25.44","field5":"25.38","field6":"51.81","field7":"13.31","field8":"46.31"},{"created_at":"2018-09-14T18:12:17Z","entry_id":245443,"field1":"34.31","field2":"8.06","field3":"23.31","field4":"25.75","field5":"25.50","field6":"51.75","field7":"13.56","field8":"46.31"},{"created_at":"2018-09-14T18:15:16Z","entry_id":245444,"field1":"34.31","field2":"7.81","field3":"23.31","field4":"25.81","field5":"25.69","field6":"51.75","field7":"13.81","field8":"46.31"},{"created_at":"2018-09-14T18:18:18Z","entry_id":245445,"field1":"34.31","field2":"7.81","field3":"23.31","field4":"26.06","field5":"25.88","field6":"51.69","field7":"14.06","field8":"46.31"},{"created_at":"2018-09-14T18:21:19Z","entry_id":245446,"field1":"34.31","field2":"7.81","field3":"23.31","field4":"26.25","field5":"26.12","field6":"51.69","field7":"14.62","field8":"46.25"},{"created_at":"2018-09-14T18:24:17Z","entry_id":245447,"field1":"34.25","field2":"7.88","field3":"23.25","field4":"26.50","field5":"26.31","field6":"51.94","field7":"11.62","field8":"46.25"},{"created_at":"2018-09-14T18:27:21Z","entry_id":245448,"field1":"34.25","field2":"7.75","field3":"23.25","field4":"26.62","field5":"26.50","field6":"51.88","field7":"11.62","field8":"46.25"},{"created_at":"2018-09-14T18:30:17Z","entry_id":245449,"field1":"34.25","field2":"7.75","field3":"23.25","field4":"26.88","field5":"26.69","field6":"51.81","field7":"11.88","field8":"46.19"},{"created_at":"2018-09-14T18:33:19Z","entry_id":245450,"field1":"34.25","field2":"7.75","field3":"23.25","field4":"26.94","field5":"26.88","field6":"51.81","field7":"12.06","field8":"46.19"},{"created_at":"2018-09-14T18:36:24Z","entry_id":245451,"field1":"34.25","field2":"7.75","field3":"23.25","field4":"27.12","field5":"27.06","field6":"51.81","field7":"12.31","field8":"46.12"},{"created_at":"2018-09-14T18:39:18Z","entry_id":245452,"field1":"34.25","field2":"7.69","field3":"23.25","field4":"27.25","field5":"27.19","field6":"51.81","field7":"12.56","field8":"46.12"},{"created_at":"2018-09-14T18:42:18Z","entry_id":245453,"field1":"34.19","field2":"7.50","field3":"23.25","field4":"27.38","field5":"27.31","field6":"51.81","field7":"12.75","field8":"46.12"},{"created_at":"2018-09-14T18:45:17Z","entry_id":245454,"field1":"34.19","field2":"7.56","field3":"23.25","field4":"27.50","field5":"27.38","field6":"51.81","field7":"13.00","field8":"46.06"},{"created_at":"2018-09-14T18:48:22Z","entry_id":245455,"field1":"34.19","field2":"7.50","field3":"23.25","field4":"85.00","field5":"27.44","field6":"51.88","field7":"15.44","field8":"46.06"},{"created_at":"2018-09-14T18:51:21Z","entry_id":245456,"field1":"34.19","field2":"7.62","field3":"23.25","field4":"85.00","field5":"27.50","field6":"52.44","field7":"15.94","field8":"46.00"},{"created_at":"2018-09-14T18:54:18Z","entry_id":245457,"field1":"34.19","field2":"7.56","field3":"23.25","field4":"27.50","field5":"27.50","field6":"52.38","field7":"16.06","field8":"46.00"},{"created_at":"2018-09-14T18:57:16Z","entry_id":245458,"field1":"34.19","field2":"7.62","field3":"23.25","field4":"27.50","field5":"27.50","field6":"52.38","field7":"16.19","field8":"45.94"},{"created_at":"2018-09-14T19:00:17Z","entry_id":245459,"field1":"34.19","field2":"7.69","field3":"23.19","field4":"27.56","field5":"27.56","field6":"52.31","field7":"16.25","field8":"45.94"},{"created_at":"2018-09-14T19:03:18Z","entry_id":245460,"field1":"34.19","field2":"7.69","field3":"23.19","field4":"27.62","field5":"27.56","field6":"52.25","field7":"16.38","field8":"45.94"},{"created_at":"2018-09-14T19:06:17Z","entry_id":245461,"field1":"34.12","field2":"7.62","field3":"23.19","field4":"85.00","field5":"27.56","field6":"52.25","field7":"16.50","field8":"45.88"},{"created_at":"2018-09-14T19:09:22Z","entry_id":245462,"field1":"34.12","field2":"7.69","field3":"23.19","field4":"27.50","field5":"27.56","field6":"52.19","field7":"16.56","field8":"45.88"},{"created_at":"2018-09-14T19:12:21Z","entry_id":245463,"field1":"34.12","field2":"7.62","field3":"23.19","field4":"27.50","field5":"27.56","field6":"52.19","field7":"16.69","field8":"45.88"},{"created_at":"2018-09-14T19:15:21Z","entry_id":245464,"field1":"34.12","field2":"7.50","field3":"23.19","field4":"85.00","field5":"27.50","field6":"52.12","field7":"16.75","field8":"45.81"},{"created_at":"2018-09-14T19:18:18Z","entry_id":245465,"field1":"34.12","field2":"7.44","field3":"23.19","field4":"27.50","field5":"27.44","field6":"52.12","field7":"16.81","field8":"45.81"},{"created_at":"2018-09-14T19:21:19Z","entry_id":245466,"field1":"34.12","field2":"7.50","field3":"23.19","field4":"27.38","field5":"27.44","field6":"52.06","field7":"16.88","field8":"45.75"},{"created_at":"2018-09-14T19:24:19Z","entry_id":245467,"field1":"34.06","field2":"7.31","field3":"23.19","field4":"85.00","field5":"27.44","field6":"52.06","field7":"17.00","field8":"45.75"},{"created_at":"2018-09-14T19:27:17Z","entry_id":245468,"field1":"34.06","field2":"7.19","field3":"23.19","field4":"27.31","field5":"27.38","field6":"52.06","field7":"17.06","field8":"45.75"},{"created_at":"2018-09-14T19:30:16Z","entry_id":245469,"field1":"34.06","field2":"7.19","field3":"23.19","field4":"27.31","field5":"27.38","field6":"52.00","field7":"17.12","field8":"45.69"},{"created_at":"2018-09-14T19:33:29Z","entry_id":245470,"field1":"34.06","field2":"7.12","field3":"23.19","field4":"27.50","field5":"27.44","field6":"52.38","field7":"17.25","field8":"45.62"},{"created_at":"2018-09-14T19:36:17Z","entry_id":245471,"field1":"34.06","field2":"7.12","field3":"23.12","field4":"27.62","field5":"27.44","field6":"52.56","field7":"17.31","field8":"45.62"},{"created_at":"2018-09-14T19:39:18Z","entry_id":245472,"field1":"34.06","field2":"7.00","field3":"23.12","field4":"85.00","field5":"27.56","field6":"52.50","field7":"17.38","field8":"45.62"},{"created_at":"2018-09-14T19:42:19Z","entry_id":245473,"field1":"34.06","field2":"6.75","field3":"23.12","field4":"28.00","field5":"27.75","field6":"52.44","field7":"17.69","field8":"45.56"},{"created_at":"2018-09-14T19:45:18Z","entry_id":245474,"field1":"34.06","field2":"6.75","field3":"23.12","field4":"85.00","field5":"27.94","field6":"52.19","field7":"14.06","field8":"45.50"},{"created_at":"2018-09-14T19:48:18Z","entry_id":245475,"field1":"34.00","field2":"7.00","field3":"23.12","field4":"28.38","field5":"28.12","field6":"51.94","field7":"11.56","field8":"45.44"},{"created_at":"2018-09-14T19:51:17Z","entry_id":245476,"field1":"34.00","field2":"6.81","field3":"23.12","field4":"28.62","field5":"28.38","field6":"51.94","field7":"11.31","field8":"45.38"},{"created_at":"2018-09-14T19:54:17Z","entry_id":245477,"field1":"34.00","field2":"6.88","field3":"23.12","field4":"28.75","field5":"28.56","field6":"51.94","field7":"12.19","field8":"45.31"},{"created_at":"2018-09-14T19:57:20Z","entry_id":245478,"field1":"33.94","field2":"6.75","field3":"23.06","field4":"28.88","field5":"28.75","field6":"51.88","field7":"12.56","field8":"45.25"},{"created_at":"2018-09-14T20:00:17Z","entry_id":245479,"field1":"33.94","field2":"6.56","field3":"23.06","field4":"29.06","field5":"28.94","field6":"52.12","field7":"12.81","field8":"45.12"},{"created_at":"2018-09-14T20:03:18Z","entry_id":245480,"field1":"33.94","field2":"6.69","field3":"23.06","field4":"29.25","field5":"29.06","field6":"52.69","field7":"13.00","field8":"45.06"},{"created_at":"2018-09-14T20:06:20Z","entry_id":245481,"field1":"33.88","field2":"6.75","field3":"23.06","field4":"85.00","field5":"29.19","field6":"52.69","field7":"13.19","field8":"45.00"},{"created_at":"2018-09-14T20:09:18Z","entry_id":245482,"field1":"33.88","field2":"6.69","field3":"23.06","field4":"29.12","field5":"29.25","field6":"52.62","field7":"13.44","field8":"44.94"},{"created_at":"2018-09-14T20:12:19Z","entry_id":245483,"field1":"33.88","field2":"6.62","field3":"23.06","field4":"29.06","field5":"29.19","field6":"52.56","field7":"13.62","field8":"44.88"},{"created_at":"2018-09-14T20:15:22Z","entry_id":245484,"field1":"33.88","field2":"6.56","field3":"23.06","field4":"29.06","field5":"29.19","field6":"52.56","field7":"13.88","field8":"44.81"},{"created_at":"2018-09-14T20:18:20Z","entry_id":245485,"field1":"33.88","field2":"6.56","field3":"23.06","field4":"29.00","field5":"29.06","field6":"52.50","field7":"14.06","field8":"44.75"},{"created_at":"2018-09-14T20:21:18Z","entry_id":245486,"field1":"33.88","field2":"6.56","field3":"23.06","field4":"28.94","field5":"29.00","field6":"52.50","field7":"14.25","field8":"44.69"},{"created_at":"2018-09-14T20:24:17Z","entry_id":245487,"field1":"33.81","field2":"6.50","field3":"23.06","field4":"28.88","field5":"29.00","field6":"52.50","field7":"14.44","field8":"44.62"},{"created_at":"2018-09-14T20:27:19Z","entry_id":245488,"field1":"33.81","field2":"6.56","field3":"23.00","field4":"29.00","field5":"28.94","field6":"52.44","field7":"14.62","field8":"44.56"},{"created_at":"2018-09-14T20:30:21Z","entry_id":245489,"field1":"33.81","field2":"6.62","field3":"23.00","field4":"85.00","field5":"28.88","field6":"52.44","field7":"14.81","field8":"44.50"},{"created_at":"2018-09-14T20:33:17Z","entry_id":245490,"field1":"33.81","field2":"6.56","field3":"23.00","field4":"28.94","field5":"28.88","field6":"52.69","field7":"15.00","field8":"44.44"},{"created_at":"2018-09-14T20:36:17Z","entry_id":245491,"field1":"33.81","field2":"6.44","field3":"23.00","field4":"29.12","field5":"28.94","field6":"53.00","field7":"15.19","field8":"44.38"},{"created_at":"2018-09-14T20:39:17Z","entry_id":245492,"field1":"33.81","field2":"6.38","field3":"23.00","field4":"85.00","field5":"29.06","field6":"52.88","field7":"15.44","field8":"44.25"},{"created_at":"2018-09-14T20:42:19Z","entry_id":245493,"field1":"33.75","field2":"6.50","field3":"22.94","field4":"85.00","field5":"29.31","field6":"52.81","field7":"15.81","field8":"44.12"},{"created_at":"2018-09-14T20:45:17Z","entry_id":245494,"field1":"33.75","field2":"6.38","field3":"22.94","field4":"29.81","field5":"29.56","field6":"52.81","field7":"16.00","field8":"44.00"},{"created_at":"2018-09-14T20:48:17Z","entry_id":245495,"field1":"33.75","field2":"6.25","field3":"22.88","field4":"30.06","field5":"29.88","field6":"52.75","field7":"16.12","field8":"43.81"},{"created_at":"2018-09-14T20:51:18Z","entry_id":245496,"field1":"33.69","field2":"6.19","field3":"22.81","field4":"30.38","field5":"30.06","field6":"52.94","field7":"16.25","field8":"43.62"},{"created_at":"2018-09-14T20:54:19Z","entry_id":245497,"field1":"33.69","field2":"6.19","field3":"22.81","field4":"85.00","field5":"30.31","field6":"53.50","field7":"16.44","field8":"43.50"},{"created_at":"2018-09-14T20:57:21Z","entry_id":245498,"field1":"33.69","field2":"5.94","field3":"22.75","field4":"30.88","field5":"30.56","field6":"53.44","field7":"16.56","field8":"43.31"},{"created_at":"2018-09-14T21:00:19Z","entry_id":245499,"field1":"33.69","field2":"6.06","field3":"22.69","field4":"85.00","field5":"30.75","field6":"53.38","field7":"20.62","field8":"43.12"},{"created_at":"2018-09-14T21:03:20Z","entry_id":245500,"field1":"33.69","field2":"6.00","field3":"22.69","field4":"31.00","field5":"30.88","field6":"53.12","field7":"14.81","field8":"42.94"},{"created_at":"2018-09-14T21:06:18Z","entry_id":245501,"field1":"33.69","field2":"6.06","field3":"22.62","field4":"31.00","field5":"30.94","field6":"52.81","field7":"12.19","field8":"42.75"},{"created_at":"2018-09-14T21:09:18Z","entry_id":245502,"field1":"33.62","field2":"6.06","field3":"22.62","field4":"30.94","field5":"30.94","field6":"52.69","field7":"11.94","field8":"42.62"},{"created_at":"2018-09-14T21:12:23Z","entry_id":245503,"field1":"33.62","field2":"6.06","field3":"22.62","field4":"30.94","field5":"30.88","field6":"52.69","field7":"12.12","field8":"42.44"},{"created_at":"2018-09-14T21:15:17Z","entry_id":245504,"field1":"33.62","field2":"6.19","field3":"22.56","field4":"30.88","field5":"30.88","field6":"52.69","field7":"12.38","field8":"42.25"},{"created_at":"2018-09-14T21:18:19Z","entry_id":245505,"field1":"33.56","field2":"6.38","field3":"22.56","field4":"30.88","field5":"30.88","field6":"52.69","field7":"12.56","field8":"42.12"},{"created_at":"2018-09-14T21:21:22Z","entry_id":245506,"field1":"33.56","field2":"6.56","field3":"22.50","field4":"31.00","field5":"30.88","field6":"52.75","field7":"12.81","field8":"41.94"},{"created_at":"2018-09-14T21:24:19Z","entry_id":245507,"field1":"33.50","field2":"6.56","field3":"22.50","field4":"31.00","field5":"30.81","field6":"53.31","field7":"13.06","field8":"41.81"},{"created_at":"2018-09-14T21:27:20Z","entry_id":245508,"field1":"33.50","field2":"6.69","field3":"22.44","field4":"85.00","field5":"30.81","field6":"53.38","field7":"13.31","field8":"41.69"},{"created_at":"2018-09-14T21:30:17Z","entry_id":245509,"field1":"33.50","field2":"7.06","field3":"22.44","field4":"30.88","field5":"30.81","field6":"53.38","field7":"13.56","field8":"41.50"},{"created_at":"2018-09-14T21:33:21Z","entry_id":245510,"field1":"33.50","field2":"7.12","field3":"22.44","field4":"85.00","field5":"30.81","field6":"53.31","field7":"13.75","field8":"41.31"},{"created_at":"2018-09-14T21:36:18Z","entry_id":245511,"field1":"33.50","field2":"7.19","field3":"22.38","field4":"31.00","field5":"30.81","field6":"53.25","field7":"14.00","field8":"41.19"},{"created_at":"2018-09-14T21:39:19Z","entry_id":245512,"field1":"33.50","field2":"7.25","field3":"22.38","field4":"31.00","field5":"30.81","field6":"53.25","field7":"14.25","field8":"40.94"},{"created_at":"2018-09-14T21:42:17Z","entry_id":245513,"field1":"33.50","field2":"7.31","field3":"22.38","field4":"31.00","field5":"30.81","field6":"53.19","field7":"14.44","field8":"40.75"},{"created_at":"2018-09-14T21:45:18Z","entry_id":245514,"field1":"33.44","field2":"7.44","field3":"22.31","field4":"31.12","field5":"30.88","field6":"53.19","field7":"14.62","field8":"40.56"},{"created_at":"2018-09-14T21:48:18Z","entry_id":245515,"field1":"33.44","field2":"7.50","field3":"22.31","field4":"31.25","field5":"31.00","field6":"53.69","field7":"14.88","field8":"40.31"},{"created_at":"2018-09-14T21:51:17Z","entry_id":245516,"field1":"33.44","field2":"7.56","field3":"22.31","field4":"31.38","field5":"31.19","field6":"53.62","field7":"15.06","field8":"40.12"},{"created_at":"2018-09-14T21:54:17Z","entry_id":245517,"field1":"33.44","field2":"7.62","field3":"22.31","field4":"31.50","field5":"31.31","field6":"53.56","field7":"15.25","field8":"39.81"},{"created_at":"2018-09-14T21:57:17Z","entry_id":245518,"field1":"33.38","field2":"7.69","field3":"22.31","field4":"85.00","field5":"31.44","field6":"53.50","field7":"15.44","field8":"39.56"},{"created_at":"2018-09-14T22:00:21Z","entry_id":245519,"field1":"33.38","field2":"7.75","field3":"22.25","field4":"85.00","field5":"31.56","field6":"53.44","field7":"15.62","field8":"39.25"},{"created_at":"2018-09-14T22:03:20Z","entry_id":245520,"field1":"33.38","field2":"7.81","field3":"22.25","field4":"85.00","field5":"31.62","field6":"53.44","field7":"15.81","field8":"39.00"},{"created_at":"2018-09-14T22:06:19Z","entry_id":245521,"field1":"33.38","field2":"7.88","field3":"22.25","field4":"85.00","field5":"31.56","field6":"53.94","field7":"16.00","field8":"38.81"},{"created_at":"2018-09-14T22:09:18Z","entry_id":245522,"field1":"33.38","field2":"7.94","field3":"22.25","field4":"31.50","field5":"31.44","field6":"53.94","field7":"16.12","field8":"38.69"},{"created_at":"2018-09-14T22:12:18Z","entry_id":245523,"field1":"33.38","field2":"8.00","field3":"22.25","field4":"31.25","field5":"31.31","field6":"53.88","field7":"16.31","field8":"38.50"},{"created_at":"2018-09-14T22:15:17Z","entry_id":245524,"field1":"33.38","field2":"8.00","field3":"22.19","field4":"31.12","field5":"31.19","field6":"53.81","field7":"16.50","field8":"38.38"},{"created_at":"2018-09-14T22:18:23Z","entry_id":245525,"field1":"33.31","field2":"8.06","field3":"22.19","field4":"85.00","field5":"31.06","field6":"53.75","field7":"16.62","field8":"38.19"},{"created_at":"2018-09-14T22:21:19Z","entry_id":245526,"field1":"33.31","field2":"8.06","field3":"22.19","field4":"30.88","field5":"30.94","field6":"53.75","field7":"16.75","field8":"38.06"},{"created_at":"2018-09-14T22:24:18Z","entry_id":245527,"field1":"33.31","field2":"8.06","field3":"22.19","field4":"30.75","field5":"30.81","field6":"53.69","field7":"16.88","field8":"37.94"},{"created_at":"2018-09-14T22:27:19Z","entry_id":245528,"field1":"33.31","field2":"8.06","field3":"22.19","field4":"30.62","field5":"30.62","field6":"53.69","field7":"17.00","field8":"37.81"},{"created_at":"2018-09-14T22:30:19Z","entry_id":245529,"field1":"33.31","field2":"8.12","field3":"22.19","field4":"30.50","field5":"30.56","field6":"53.62","field7":"17.12","field8":"37.75"},{"created_at":"2018-09-14T22:33:23Z","entry_id":245530,"field1":"33.25","field2":"8.12","field3":"22.19","field4":"30.50","field5":"30.44","field6":"53.62","field7":"17.25","field8":"37.56"},{"created_at":"2018-09-14T22:36:17Z","entry_id":245531,"field1":"33.25","field2":"8.06","field3":"22.19","field4":"30.38","field5":"30.38","field6":"53.56","field7":"17.38","field8":"37.44"},{"created_at":"2018-09-14T22:39:21Z","entry_id":245532,"field1":"33.25","field2":"8.12","field3":"22.12","field4":"30.25","field5":"30.31","field6":"53.88","field7":"17.50","field8":"37.31"},{"created_at":"2018-09-14T22:42:20Z","entry_id":245533,"field1":"33.25","field2":"8.12","field3":"22.12","field4":"30.19","field5":"30.19","field6":"54.00","field7":"17.56","field8":"37.19"},{"created_at":"2018-09-14T22:45:19Z","entry_id":245534,"field1":"33.25","field2":"8.12","field3":"22.12","field4":"85.00","field5":"30.19","field6":"53.94","field7":"17.69","field8":"37.06"},{"created_at":"2018-09-14T22:48:17Z","entry_id":245535,"field1":"33.25","field2":"8.06","field3":"22.12","field4":"30.38","field5":"30.19","field6":"53.94","field7":"17.75","field8":"36.88"},{"created_at":"2018-09-14T22:51:23Z","entry_id":245536,"field1":"33.25","field2":"8.06","field3":"22.12","field4":"30.50","field5":"30.31","field6":"53.88","field7":"17.88","field8":"36.69"},{"created_at":"2018-09-14T22:54:17Z","entry_id":245537,"field1":"33.25","field2":"8.12","field3":"22.06","field4":"30.62","field5":"30.31","field6":"53.88","field7":"17.94","field8":"36.50"},{"created_at":"2018-09-14T22:57:19Z","entry_id":245538,"field1":"33.25","field2":"8.06","field3":"22.06","field4":"85.00","field5":"30.44","field6":"53.81","field7":"18.06","field8":"36.31"},{"created_at":"2018-09-14T23:00:19Z","entry_id":245539,"field1":"33.25","field2":"8.06","field3":"22.06","field4":"85.00","field5":"30.50","field6":"53.81","field7":"18.12","field8":"36.12"},{"created_at":"2018-09-14T23:03:17Z","entry_id":245540,"field1":"33.19","field2":"8.06","field3":"22.06","field4":"30.88","field5":"30.56","field6":"53.94","field7":"18.19","field8":"35.88"}]}