{"channel":{"id":302387,"name":"Radmon","description":"Radiation monitor","latitude":"51.813542","longitude":"5.797562","field1":"CPM","field2":"Dose","field3":"RSSI","field8":"Charge","created_at":"2017-07-13T20:22:56Z","updated_at":"2018-09-06T05:51:31Z","elevation":"0","last_entry_id":108439},"feeds":[{"created_at":"2018-09-05T20:49:41Z","entry_id":108340,"field1":"16","field2":"0.09","field3":"2.00","field8":null},{"created_at":"2018-09-05T20:55:09Z","entry_id":108341,"field1":"11","field2":"0.06","field3":"2.00","field8":null},{"created_at":"2018-09-05T21:00:37Z","entry_id":108342,"field1":"12","field2":"0.07","field3":"2.00","field8":null},{"created_at":"2018-09-05T21:06:06Z","entry_id":108343,"field1":"13","field2":"0.07","field3":"2.00","field8":null},{"created_at":"2018-09-05T21:11:34Z","entry_id":108344,"field1":"12","field2":"0.07","field3":"2.00","field8":null},{"created_at":"2018-09-05T21:17:02Z","entry_id":108345,"field1":"14","field2":"0.08","field3":"2.00","field8":null},{"created_at":"2018-09-05T21:22:30Z","entry_id":108346,"field1":"13","field2":"0.07","field3":"2.00","field8":null},{"created_at":"2018-09-05T21:27:59Z","entry_id":108347,"field1":"12","field2":"0.07","field3":"2.00","field8":null},{"created_at":"2018-09-05T21:33:27Z","entry_id":108348,"field1":"12","field2":"0.07","field3":"2.00","field8":null},{"created_at":"2018-09-05T21:38:55Z","entry_id":108349,"field1":"13","field2":"0.07","field3":"2.00","field8":null},{"created_at":"2018-09-05T21:44:23Z","entry_id":108350,"field1":"12","field2":"0.07","field3":"2.00","field8":null},{"created_at":"2018-09-05T21:49:52Z","entry_id":108351,"field1":"15","field2":"0.09","field3":"2.00","field8":null},{"created_at":"2018-09-05T21:55:20Z","entry_id":108352,"field1":"14","field2":"0.08","field3":"2.00","field8":null},{"created_at":"2018-09-05T22:00:48Z","entry_id":108353,"field1":"10","field2":"0.06","field3":"3.00","field8":null},{"created_at":"2018-09-05T22:06:16Z","entry_id":108354,"field1":"13","field2":"0.07","field3":"2.00","field8":null},{"created_at":"2018-09-05T22:11:44Z","entry_id":108355,"field1":"12","field2":"0.07","field3":"3.00","field8":null},{"created_at":"2018-09-05T22:17:13Z","entry_id":108356,"field1":"14","field2":"0.08","field3":"2.00","field8":null},{"created_at":"2018-09-05T22:22:41Z","entry_id":108357,"field1":"12","field2":"0.07","field3":"2.00","field8":null},{"created_at":"2018-09-05T22:28:09Z","entry_id":108358,"field1":"12","field2":"0.07","field3":"2.00","field8":null},{"created_at":"2018-09-05T22:33:37Z","entry_id":108359,"field1":"11","field2":"0.06","field3":"2.00","field8":null},{"created_at":"2018-09-05T22:39:06Z","entry_id":108360,"field1":"15","field2":"0.09","field3":"3.00","field8":null},{"created_at":"2018-09-05T22:44:34Z","entry_id":108361,"field1":"13","field2":"0.07","field3":"2.00","field8":null},{"created_at":"2018-09-05T22:50:02Z","entry_id":108362,"field1":"12","field2":"0.07","field3":"3.00","field8":null},{"created_at":"2018-09-05T22:55:30Z","entry_id":108363,"field1":"13","field2":"0.07","field3":"2.00","field8":null},{"created_at":"2018-09-05T23:00:58Z","entry_id":108364,"field1":"13","field2":"0.07","field3":"2.00","field8":null},{"created_at":"2018-09-05T23:06:28Z","entry_id":108365,"field1":"11","field2":"0.06","field3":"2.00","field8":null},{"created_at":"2018-09-05T23:11:56Z","entry_id":108366,"field1":"12","field2":"0.07","field3":"2.00","field8":null},{"created_at":"2018-09-05T23:17:24Z","entry_id":108367,"field1":"15","field2":"0.09","field3":"2.00","field8":null},{"created_at":"2018-09-05T23:22:52Z","entry_id":108368,"field1":"12","field2":"0.07","field3":"3.00","field8":null},{"created_at":"2018-09-05T23:28:20Z","entry_id":108369,"field1":"10","field2":"0.06","field3":"2.00","field8":null},{"created_at":"2018-09-05T23:33:49Z","entry_id":108370,"field1":"15","field2":"0.09","field3":"2.00","field8":null},{"created_at":"2018-09-05T23:39:17Z","entry_id":108371,"field1":"13","field2":"0.07","field3":"0.00","field8":null},{"created_at":"2018-09-05T23:44:46Z","entry_id":108372,"field1":"14","field2":"0.08","field3":"2.00","field8":null},{"created_at":"2018-09-05T23:50:14Z","entry_id":108373,"field1":"10","field2":"0.06","field3":"3.00","field8":null},{"created_at":"2018-09-05T23:55:43Z","entry_id":108374,"field1":"13","field2":"0.07","field3":"2.00","field8":null},{"created_at":"2018-09-06T00:01:11Z","entry_id":108375,"field1":"13","field2":"0.07","field3":"3.00","field8":null},{"created_at":"2018-09-06T00:06:39Z","entry_id":108376,"field1":"12","field2":"0.07","field3":"1.00","field8":null},{"created_at":"2018-09-06T00:12:08Z","entry_id":108377,"field1":"11","field2":"0.06","field3":"2.00","field8":null},{"created_at":"2018-09-06T00:17:36Z","entry_id":108378,"field1":"15","field2":"0.09","field3":"2.00","field8":null},{"created_at":"2018-09-06T00:23:04Z","entry_id":108379,"field1":"13","field2":"0.07","field3":"2.00","field8":null},{"created_at":"2018-09-06T00:28:32Z","entry_id":108380,"field1":"16","field2":"0.09","field3":"2.00","field8":null},{"created_at":"2018-09-06T00:34:01Z","entry_id":108381,"field1":"12","field2":"0.07","field3":"2.00","field8":null},{"created_at":"2018-09-06T00:39:29Z","entry_id":108382,"field1":"14","field2":"0.08","field3":"2.00","field8":null},{"created_at":"2018-09-06T00:44:57Z","entry_id":108383,"field1":"15","field2":"0.09","field3":"2.00","field8":null},{"created_at":"2018-09-06T00:50:25Z","entry_id":108384,"field1":"12","field2":"0.07","field3":"2.00","field8":null},{"created_at":"2018-09-06T00:55:54Z","entry_id":108385,"field1":"16","field2":"0.09","field3":"2.00","field8":null},{"created_at":"2018-09-06T01:01:22Z","entry_id":108386,"field1":"15","field2":"0.09","field3":"2.00","field8":null},{"created_at":"2018-09-06T01:06:50Z","entry_id":108387,"field1":"12","field2":"0.07","field3":"3.00","field8":null},{"created_at":"2018-09-06T01:12:19Z","entry_id":108388,"field1":"10","field2":"0.06","field3":"2.00","field8":null},{"created_at":"2018-09-06T01:17:54Z","entry_id":108389,"field1":"13","field2":"0.07","field3":"2.00","field8":null},{"created_at":"2018-09-06T01:23:20Z","entry_id":108390,"field1":"12","field2":"0.07","field3":"2.00","field8":null},{"created_at":"2018-09-06T01:28:48Z","entry_id":108391,"field1":"12","field2":"0.07","field3":"2.00","field8":null},{"created_at":"2018-09-06T01:34:16Z","entry_id":108392,"field1":"13","field2":"0.07","field3":"3.00","field8":null},{"created_at":"2018-09-06T01:39:44Z","entry_id":108393,"field1":"13","field2":"0.07","field3":"2.00","field8":null},{"created_at":"2018-09-06T01:45:13Z","entry_id":108394,"field1":"14","field2":"0.08","field3":"2.00","field8":null},{"created_at":"2018-09-06T01:50:41Z","entry_id":108395,"field1":"14","field2":"0.08","field3":"2.00","field8":null},{"created_at":"2018-09-06T01:56:09Z","entry_id":108396,"field1":"15","field2":"0.09","field3":"3.00","field8":null},{"created_at":"2018-09-06T02:01:37Z","entry_id":108397,"field1":"10","field2":"0.06","field3":"2.00","field8":null},{"created_at":"2018-09-06T02:07:05Z","entry_id":108398,"field1":"13","field2":"0.07","field3":"2.00","field8":null},{"created_at":"2018-09-06T02:12:34Z","entry_id":108399,"field1":"12","field2":"0.07","field3":"3.00","field8":null},{"created_at":"2018-09-06T02:18:02Z","entry_id":108400,"field1":"15","field2":"0.09","field3":"2.00","field8":null},{"created_at":"2018-09-06T02:23:30Z","entry_id":108401,"field1":"11","field2":"0.06","field3":"2.00","field8":null},{"created_at":"2018-09-06T02:28:58Z","entry_id":108402,"field1":"10","field2":"0.06","field3":"2.00","field8":null},{"created_at":"2018-09-06T02:34:27Z","entry_id":108403,"field1":"13","field2":"0.07","field3":"2.00","field8":null},{"created_at":"2018-09-06T02:39:55Z","entry_id":108404,"field1":"12","field2":"0.07","field3":"3.00","field8":null},{"created_at":"2018-09-06T02:45:23Z","entry_id":108405,"field1":"11","field2":"0.06","field3":"2.00","field8":null},{"created_at":"2018-09-06T02:50:51Z","entry_id":108406,"field1":"15","field2":"0.09","field3":"2.00","field8":null},{"created_at":"2018-09-06T02:56:20Z","entry_id":108407,"field1":"10","field2":"0.06","field3":"2.00","field8":null},{"created_at":"2018-09-06T03:01:48Z","entry_id":108408,"field1":"14","field2":"0.08","field3":"2.00","field8":null},{"created_at":"2018-09-06T03:07:16Z","entry_id":108409,"field1":"14","field2":"0.08","field3":"2.00","field8":null},{"created_at":"2018-09-06T03:12:45Z","entry_id":108410,"field1":"13","field2":"0.07","field3":"2.00","field8":null},{"created_at":"2018-09-06T03:18:15Z","entry_id":108411,"field1":"14","field2":"0.08","field3":"2.00","field8":null},{"created_at":"2018-09-06T03:23:44Z","entry_id":108412,"field1":"12","field2":"0.07","field3":"2.00","field8":null},{"created_at":"2018-09-06T03:29:13Z","entry_id":108413,"field1":"15","field2":"0.09","field3":"2.00","field8":null},{"created_at":"2018-09-06T03:34:41Z","entry_id":108414,"field1":"14","field2":"0.08","field3":"2.00","field8":null},{"created_at":"2018-09-06T03:40:10Z","entry_id":108415,"field1":"12","field2":"0.07","field3":"-12.00","field8":null},{"created_at":"2018-09-06T03:45:38Z","entry_id":108416,"field1":"12","field2":"0.07","field3":"2.00","field8":null},{"created_at":"2018-09-06T03:51:06Z","entry_id":108417,"field1":"14","field2":"0.08","field3":"2.00","field8":null},{"created_at":"2018-09-06T03:56:35Z","entry_id":108418,"field1":"13","field2":"0.07","field3":"2.00","field8":null},{"created_at":"2018-09-06T04:02:03Z","entry_id":108419,"field1":"14","field2":"0.08","field3":"2.00","field8":null},{"created_at":"2018-09-06T04:07:31Z","entry_id":108420,"field1":"14","field2":"0.08","field3":"2.00","field8":null},{"created_at":"2018-09-06T04:13:00Z","entry_id":108421,"field1":"12","field2":"0.07","field3":"2.00","field8":null},{"created_at":"2018-09-06T04:18:28Z","entry_id":108422,"field1":"14","field2":"0.08","field3":"3.00","field8":null},{"created_at":"2018-09-06T04:23:56Z","entry_id":108423,"field1":"12","field2":"0.07","field3":"3.00","field8":null},{"created_at":"2018-09-06T04:29:25Z","entry_id":108424,"field1":"12","field2":"0.07","field3":"2.00","field8":null},{"created_at":"2018-09-06T04:34:53Z","entry_id":108425,"field1":"12","field2":"0.07","field3":"2.00","field8":null},{"created_at":"2018-09-06T04:40:21Z","entry_id":108426,"field1":"14","field2":"0.08","field3":"2.00","field8":null},{"created_at":"2018-09-06T04:45:50Z","entry_id":108427,"field1":"12","field2":"0.07","field3":"2.00","field8":null},{"created_at":"2018-09-06T04:51:19Z","entry_id":108428,"field1":"10","field2":"0.06","field3":"2.00","field8":null},{"created_at":"2018-09-06T04:56:47Z","entry_id":108429,"field1":"11","field2":"0.06","field3":"2.00","field8":null},{"created_at":"2018-09-06T05:02:16Z","entry_id":108430,"field1":"11","field2":"0.06","field3":"2.00","field8":null},{"created_at":"2018-09-06T05:07:44Z","entry_id":108431,"field1":"14","field2":"0.08","field3":"2.00","field8":null},{"created_at":"2018-09-06T05:13:12Z","entry_id":108432,"field1":"11","field2":"0.06","field3":"2.00","field8":null},{"created_at":"2018-09-06T05:18:41Z","entry_id":108433,"field1":"14","field2":"0.08","field3":"2.00","field8":null},{"created_at":"2018-09-06T05:24:09Z","entry_id":108434,"field1":"11","field2":"0.06","field3":"2.00","field8":null},{"created_at":"2018-09-06T05:29:37Z","entry_id":108435,"field1":"11","field2":"0.06","field3":"2.00","field8":null},{"created_at":"2018-09-06T05:35:06Z","entry_id":108436,"field1":"13","field2":"0.07","field3":"2.00","field8":null},{"created_at":"2018-09-06T05:40:34Z","entry_id":108437,"field1":"15","field2":"0.09","field3":"2.00","field8":null},{"created_at":"2018-09-06T05:46:02Z","entry_id":108438,"field1":"11","field2":"0.06","field3":"2.00","field8":null},{"created_at":"2018-09-06T05:51:31Z","entry_id":108439,"field1":"13","field2":"0.07","field3":"2.00","field8":null}]}