{"channel":{"id":430988,"name":"4F_0518_SMSF","description":"4F 장비실 좌측 4F_0518_SMSF 온습도\r\n장비:#3","latitude":"0.0","longitude":"0.0","field1":"4F_0518_SMSF_온도","field2":"4F_0518_SMSF_습도","created_at":"2018-02-20T08:12:49Z","updated_at":"2018-09-14T23:23:38Z","last_entry_id":89524},"feeds":[{"created_at":"2018-09-14T18:25:26Z","entry_id":89425,"field1":"23.6","field2":"42.1"},{"created_at":"2018-09-14T18:28:27Z","entry_id":89426,"field1":"23.2","field2":"43.7"},{"created_at":"2018-09-14T18:31:27Z","entry_id":89427,"field1":"23.2","field2":"44.7"},{"created_at":"2018-09-14T18:34:28Z","entry_id":89428,"field1":"23.6","field2":"43.2"},{"created_at":"2018-09-14T18:37:28Z","entry_id":89429,"field1":"23.3","field2":"42.9"},{"created_at":"2018-09-14T18:40:29Z","entry_id":89430,"field1":"22.7","field2":"43.4"},{"created_at":"2018-09-14T18:43:30Z","entry_id":89431,"field1":"22.8","field2":"43"},{"created_at":"2018-09-14T18:46:30Z","entry_id":89432,"field1":"22.5","field2":"43.1"},{"created_at":"2018-09-14T18:49:31Z","entry_id":89433,"field1":"22.9","field2":"43"},{"created_at":"2018-09-14T18:52:32Z","entry_id":89434,"field1":"23.1","field2":"41.6"},{"created_at":"2018-09-14T18:55:33Z","entry_id":89435,"field1":"23.3","field2":"42.8"},{"created_at":"2018-09-14T18:58:33Z","entry_id":89436,"field1":"22.7","field2":"44.1"},{"created_at":"2018-09-14T19:01:34Z","entry_id":89437,"field1":"22.5","field2":"44.3"},{"created_at":"2018-09-14T19:04:35Z","entry_id":89438,"field1":"22.4","field2":"44.5"},{"created_at":"2018-09-14T19:07:36Z","entry_id":89439,"field1":"22.5","field2":"43.9"},{"created_at":"2018-09-14T19:10:36Z","entry_id":89440,"field1":"22.4","field2":"43.8"},{"created_at":"2018-09-14T19:13:37Z","entry_id":89441,"field1":"23.3","field2":"41.9"},{"created_at":"2018-09-14T19:16:38Z","entry_id":89442,"field1":"23.5","field2":"40.7"},{"created_at":"2018-09-14T19:19:39Z","entry_id":89443,"field1":"23.3","field2":"41"},{"created_at":"2018-09-14T19:22:40Z","entry_id":89444,"field1":"22.2","field2":"44.8"},{"created_at":"2018-09-14T19:25:40Z","entry_id":89445,"field1":"22.6","field2":"44.4"},{"created_at":"2018-09-14T19:28:41Z","entry_id":89446,"field1":"23.4","field2":"42.6"},{"created_at":"2018-09-14T19:31:42Z","entry_id":89447,"field1":"23.6","field2":"41.9"},{"created_at":"2018-09-14T19:34:43Z","entry_id":89448,"field1":"23.4","field2":"42.2"},{"created_at":"2018-09-14T19:37:43Z","entry_id":89449,"field1":"23.1","field2":"42.1"},{"created_at":"2018-09-14T19:40:44Z","entry_id":89450,"field1":"23","field2":"42.8"},{"created_at":"2018-09-14T19:43:45Z","entry_id":89451,"field1":"23.1","field2":"42.9"},{"created_at":"2018-09-14T19:46:46Z","entry_id":89452,"field1":"23","field2":"43"},{"created_at":"2018-09-14T19:49:47Z","entry_id":89453,"field1":"23.2","field2":"42"},{"created_at":"2018-09-14T19:52:47Z","entry_id":89454,"field1":"23.3","field2":"42.1"},{"created_at":"2018-09-14T19:55:48Z","entry_id":89455,"field1":"23.4","field2":"41"},{"created_at":"2018-09-14T19:58:48Z","entry_id":89456,"field1":"22.7","field2":"41.3"},{"created_at":"2018-09-14T20:01:49Z","entry_id":89457,"field1":"22","field2":"44"},{"created_at":"2018-09-14T20:04:49Z","entry_id":89458,"field1":"22","field2":"44.5"},{"created_at":"2018-09-14T20:07:51Z","entry_id":89459,"field1":"21.9","field2":"45.7"},{"created_at":"2018-09-14T20:10:51Z","entry_id":89460,"field1":"22.2","field2":"45.9"},{"created_at":"2018-09-14T20:13:52Z","entry_id":89461,"field1":"22.9","field2":"44"},{"created_at":"2018-09-14T20:16:52Z","entry_id":89462,"field1":"23.6","field2":"42.3"},{"created_at":"2018-09-14T20:19:52Z","entry_id":89463,"field1":"22.4","field2":"45.8"},{"created_at":"2018-09-14T20:22:53Z","entry_id":89464,"field1":"22.6","field2":"45"},{"created_at":"2018-09-14T20:25:54Z","entry_id":89465,"field1":"22.8","field2":"44"},{"created_at":"2018-09-14T20:28:55Z","entry_id":89466,"field1":"23","field2":"44.8"},{"created_at":"2018-09-14T20:31:55Z","entry_id":89467,"field1":"23","field2":"44.3"},{"created_at":"2018-09-14T20:34:56Z","entry_id":89468,"field1":"23.3","field2":"43.8"},{"created_at":"2018-09-14T20:37:57Z","entry_id":89469,"field1":"23.1","field2":"43.1"},{"created_at":"2018-09-14T20:40:58Z","entry_id":89470,"field1":"23","field2":"43.1"},{"created_at":"2018-09-14T20:43:59Z","entry_id":89471,"field1":"22.7","field2":"43"},{"created_at":"2018-09-14T20:46:59Z","entry_id":89472,"field1":"22.3","field2":"43.6"},{"created_at":"2018-09-14T20:50:00Z","entry_id":89473,"field1":"22.8","field2":"43"},{"created_at":"2018-09-14T20:53:01Z","entry_id":89474,"field1":"23.4","field2":"41.5"},{"created_at":"2018-09-14T20:56:01Z","entry_id":89475,"field1":"23.1","field2":"41.9"},{"created_at":"2018-09-14T20:59:02Z","entry_id":89476,"field1":"22.9","field2":"41.8"},{"created_at":"2018-09-14T21:02:03Z","entry_id":89477,"field1":"22.2","field2":"43.2"},{"created_at":"2018-09-14T21:05:04Z","entry_id":89478,"field1":"22.5","field2":"42.9"},{"created_at":"2018-09-14T21:08:04Z","entry_id":89479,"field1":"22.1","field2":"42.5"},{"created_at":"2018-09-14T21:11:05Z","entry_id":89480,"field1":"22","field2":"44.6"},{"created_at":"2018-09-14T21:14:06Z","entry_id":89481,"field1":"23.2","field2":"42.6"},{"created_at":"2018-09-14T21:17:06Z","entry_id":89482,"field1":"23.7","field2":"41.3"},{"created_at":"2018-09-14T21:20:07Z","entry_id":89483,"field1":"22.9","field2":"43.3"},{"created_at":"2018-09-14T21:23:08Z","entry_id":89484,"field1":"23","field2":"43.6"},{"created_at":"2018-09-14T21:26:09Z","entry_id":89485,"field1":"23.3","field2":"42.9"},{"created_at":"2018-09-14T21:29:09Z","entry_id":89486,"field1":"22.9","field2":"43.8"},{"created_at":"2018-09-14T21:32:10Z","entry_id":89487,"field1":"23","field2":"43.7"},{"created_at":"2018-09-14T21:35:11Z","entry_id":89488,"field1":"22.6","field2":"45.1"},{"created_at":"2018-09-14T21:38:12Z","entry_id":89489,"field1":"22.8","field2":"44.8"},{"created_at":"2018-09-14T21:41:12Z","entry_id":89490,"field1":"23.3","field2":"43.6"},{"created_at":"2018-09-14T21:44:13Z","entry_id":89491,"field1":"23","field2":"43"},{"created_at":"2018-09-14T21:47:14Z","entry_id":89492,"field1":"22.9","field2":"43.3"},{"created_at":"2018-09-14T21:50:15Z","entry_id":89493,"field1":"23.5","field2":"42.7"},{"created_at":"2018-09-14T21:53:15Z","entry_id":89494,"field1":"23.6","field2":"42.1"},{"created_at":"2018-09-14T21:56:16Z","entry_id":89495,"field1":"23.8","field2":"41.3"},{"created_at":"2018-09-14T21:59:17Z","entry_id":89496,"field1":"22.7","field2":"42.2"},{"created_at":"2018-09-14T22:02:18Z","entry_id":89497,"field1":"22.3","field2":"43"},{"created_at":"2018-09-14T22:05:18Z","entry_id":89498,"field1":"22.3","field2":"42.8"},{"created_at":"2018-09-14T22:08:19Z","entry_id":89499,"field1":"22.1","field2":"43.3"},{"created_at":"2018-09-14T22:11:20Z","entry_id":89500,"field1":"22.4","field2":"43.9"},{"created_at":"2018-09-14T22:14:21Z","entry_id":89501,"field1":"22.7","field2":"41.9"},{"created_at":"2018-09-14T22:17:21Z","entry_id":89502,"field1":"22.8","field2":"43.1"},{"created_at":"2018-09-14T22:20:22Z","entry_id":89503,"field1":"23.3","field2":"43.2"},{"created_at":"2018-09-14T22:23:23Z","entry_id":89504,"field1":"23.2","field2":"44.2"},{"created_at":"2018-09-14T22:26:24Z","entry_id":89505,"field1":"23.1","field2":"44.7"},{"created_at":"2018-09-14T22:29:25Z","entry_id":89506,"field1":"23","field2":"44.6"},{"created_at":"2018-09-14T22:32:25Z","entry_id":89507,"field1":"22.8","field2":"44.9"},{"created_at":"2018-09-14T22:35:26Z","entry_id":89508,"field1":"22.5","field2":"46"},{"created_at":"2018-09-14T22:38:27Z","entry_id":89509,"field1":"22.9","field2":"46.2"},{"created_at":"2018-09-14T22:41:28Z","entry_id":89510,"field1":"22.8","field2":"44.7"},{"created_at":"2018-09-14T22:44:29Z","entry_id":89511,"field1":"23.2","field2":"44.7"},{"created_at":"2018-09-14T22:47:29Z","entry_id":89512,"field1":"23.1","field2":"44.3"},{"created_at":"2018-09-14T22:50:30Z","entry_id":89513,"field1":"23.7","field2":"43.2"},{"created_at":"2018-09-14T22:53:31Z","entry_id":89514,"field1":"23.2","field2":"43.7"},{"created_at":"2018-09-14T22:56:31Z","entry_id":89515,"field1":"23.6","field2":"42.9"},{"created_at":"2018-09-14T22:59:32Z","entry_id":89516,"field1":"22.8","field2":"44.5"},{"created_at":"2018-09-14T23:02:33Z","entry_id":89517,"field1":"22.7","field2":"44.6"},{"created_at":"2018-09-14T23:05:33Z","entry_id":89518,"field1":"22.7","field2":"44.4"},{"created_at":"2018-09-14T23:08:34Z","entry_id":89519,"field1":"22.8","field2":"44"},{"created_at":"2018-09-14T23:11:35Z","entry_id":89520,"field1":"22.5","field2":"43.4"},{"created_at":"2018-09-14T23:14:36Z","entry_id":89521,"field1":"23","field2":"41.8"},{"created_at":"2018-09-14T23:17:37Z","entry_id":89522,"field1":"23.2","field2":"41.6"},{"created_at":"2018-09-14T23:20:37Z","entry_id":89523,"field1":"22.6","field2":"42.8"},{"created_at":"2018-09-14T23:23:38Z","entry_id":89524,"field1":"22.8","field2":"42.7"}]}