{"channel":{"id":496510,"name":"Real Time Distance Measurement","description":"Data shows the measurement of distance between sensor HC-SR04 and object and data transmitting on 2G network via module SIM900A on prepaid SIM controlled by Arduino Uno R3.","latitude":"0.0","longitude":"0.0","field1":"Distance","field2":"temperature","field3":"voltage","created_at":"2018-05-15T19:33:04Z","updated_at":"2018-09-09T08:27:46Z","last_entry_id":137},"feeds":[{"created_at":"2018-09-09T10:00:30Z","entry_id":38,"field1":"1434.00","field2":"36.74","field3":"5.14"},{"created_at":"2018-09-09T10:01:42Z","entry_id":39,"field1":"1433.00","field2":"36.75","field3":"5.14"},{"created_at":"2018-09-09T10:02:54Z","entry_id":40,"field1":"11276.00","field2":"36.75","field3":"5.14"},{"created_at":"2018-09-09T10:04:05Z","entry_id":41,"field1":"11276.00","field2":"36.74","field3":"5.14"},{"created_at":"2018-09-09T10:05:17Z","entry_id":42,"field1":"11271.00","field2":"36.69","field3":"5.14"},{"created_at":"2018-09-09T10:06:29Z","entry_id":43,"field1":"11276.00","field2":"36.68","field3":"5.14"},{"created_at":"2018-09-09T10:07:41Z","entry_id":44,"field1":"11276.00","field2":"36.63","field3":"5.14"},{"created_at":"2018-09-09T10:08:52Z","entry_id":45,"field1":"11277.00","field2":"36.63","field3":"5.14"},{"created_at":"2018-09-09T10:10:04Z","entry_id":46,"field1":"11275.00","field2":"36.63","field3":"5.14"},{"created_at":"2018-09-09T10:11:16Z","entry_id":47,"field1":"11276.00","field2":"36.62","field3":"5.14"},{"created_at":"2018-09-09T10:12:27Z","entry_id":48,"field1":"11277.00","field2":"36.63","field3":"5.14"},{"created_at":"2018-09-09T10:13:39Z","entry_id":49,"field1":"11275.00","field2":"36.62","field3":"5.14"},{"created_at":"2018-09-09T10:14:51Z","entry_id":50,"field1":"11276.00","field2":"36.62","field3":"5.14"},{"created_at":"2018-09-09T10:16:02Z","entry_id":51,"field1":"11276.00","field2":"36.61","field3":"5.14"},{"created_at":"2018-09-09T10:17:14Z","entry_id":52,"field1":"11275.00","field2":"36.62","field3":"5.14"},{"created_at":"2018-09-09T10:18:26Z","entry_id":53,"field1":"11249.00","field2":"36.59","field3":"5.14"},{"created_at":"2018-09-09T10:19:38Z","entry_id":54,"field1":"11277.00","field2":"36.56","field3":"5.14"},{"created_at":"2018-09-09T10:20:49Z","entry_id":55,"field1":"11271.00","field2":"36.56","field3":"5.12"},{"created_at":"2018-09-09T10:22:01Z","entry_id":56,"field1":"11277.00","field2":"36.56","field3":"5.14"},{"created_at":"2018-09-09T10:23:13Z","entry_id":57,"field1":"11276.00","field2":"36.57","field3":"5.14"},{"created_at":"2018-09-09T10:24:24Z","entry_id":58,"field1":"11271.00","field2":"36.61","field3":"5.14"},{"created_at":"2018-09-09T10:25:36Z","entry_id":59,"field1":"11277.00","field2":"36.61","field3":"5.14"},{"created_at":"2018-09-09T10:26:48Z","entry_id":60,"field1":"11277.00","field2":"36.63","field3":"5.14"},{"created_at":"2018-09-09T10:27:59Z","entry_id":61,"field1":"11274.00","field2":"36.63","field3":"5.14"},{"created_at":"2018-09-09T10:29:11Z","entry_id":62,"field1":"11275.00","field2":"36.63","field3":"5.14"},{"created_at":"2018-09-09T10:30:23Z","entry_id":63,"field1":"11277.00","field2":"36.63","field3":"5.14"},{"created_at":"2018-09-09T10:31:34Z","entry_id":64,"field1":"11275.00","field2":"36.63","field3":"5.14"},{"created_at":"2018-09-09T10:32:46Z","entry_id":65,"field1":"11275.00","field2":"36.63","field3":"5.14"},{"created_at":"2018-09-09T10:33:58Z","entry_id":66,"field1":"11277.00","field2":"36.62","field3":"5.14"},{"created_at":"2018-09-09T10:35:10Z","entry_id":67,"field1":"11272.00","field2":"36.60","field3":"5.14"},{"created_at":"2018-09-09T10:36:21Z","entry_id":68,"field1":"11271.00","field2":"36.61","field3":"5.14"},{"created_at":"2018-09-09T10:37:33Z","entry_id":69,"field1":"11275.00","field2":"36.62","field3":"5.14"},{"created_at":"2018-09-09T10:38:45Z","entry_id":70,"field1":"11276.00","field2":"36.63","field3":"5.14"},{"created_at":"2018-09-09T10:39:56Z","entry_id":71,"field1":"11275.00","field2":"36.63","field3":"5.14"},{"created_at":"2018-09-09T10:41:08Z","entry_id":72,"field1":"11275.00","field2":"36.63","field3":"5.14"},{"created_at":"2018-09-09T10:42:20Z","entry_id":73,"field1":"11276.00","field2":"36.62","field3":"5.14"},{"created_at":"2018-09-09T10:43:31Z","entry_id":74,"field1":"11277.00","field2":"36.63","field3":"5.14"},{"created_at":"2018-09-09T10:44:43Z","entry_id":75,"field1":"11275.00","field2":"36.63","field3":"5.14"},{"created_at":"2018-09-09T10:45:55Z","entry_id":76,"field1":"11277.00","field2":"36.64","field3":"5.14"},{"created_at":"2018-09-09T10:47:07Z","entry_id":77,"field1":"11277.00","field2":"36.63","field3":"5.14"},{"created_at":"2018-09-09T10:48:18Z","entry_id":78,"field1":"11275.00","field2":"36.63","field3":"5.14"},{"created_at":"2018-09-09T10:49:30Z","entry_id":79,"field1":"11275.00","field2":"36.63","field3":"5.14"},{"created_at":"2018-09-09T10:50:42Z","entry_id":80,"field1":"11276.00","field2":"36.63","field3":"5.14"},{"created_at":"2018-09-09T10:51:53Z","entry_id":81,"field1":"11275.00","field2":"36.63","field3":"5.14"},{"created_at":"2018-09-09T10:53:05Z","entry_id":82,"field1":"11277.00","field2":"36.66","field3":"5.14"},{"created_at":"2018-09-09T10:54:17Z","entry_id":83,"field1":"11277.00","field2":"36.68","field3":"5.14"},{"created_at":"2018-09-09T10:55:29Z","entry_id":84,"field1":"11277.00","field2":"36.68","field3":"5.14"},{"created_at":"2018-09-09T10:56:41Z","entry_id":85,"field1":"11270.00","field2":"36.69","field3":"5.14"},{"created_at":"2018-09-09T10:57:52Z","entry_id":86,"field1":"11270.00","field2":"36.68","field3":"5.14"},{"created_at":"2018-09-09T10:59:04Z","entry_id":87,"field1":"11273.00","field2":"36.69","field3":"5.12"},{"created_at":"2018-09-09T11:00:15Z","entry_id":88,"field1":"11271.00","field2":"36.67","field3":"5.14"},{"created_at":"2018-09-09T11:01:27Z","entry_id":89,"field1":"11270.00","field2":"36.64","field3":"5.14"},{"created_at":"2018-09-09T11:02:39Z","entry_id":90,"field1":"11271.00","field2":"36.66","field3":"5.14"},{"created_at":"2018-09-09T11:03:50Z","entry_id":91,"field1":"11271.00","field2":"36.68","field3":"5.14"},{"created_at":"2018-09-09T11:05:02Z","entry_id":92,"field1":"11271.00","field2":"36.69","field3":"5.14"},{"created_at":"2018-09-09T11:06:14Z","entry_id":93,"field1":"11271.00","field2":"36.68","field3":"5.14"},{"created_at":"2018-09-09T11:07:25Z","entry_id":94,"field1":"11270.00","field2":"36.69","field3":"5.14"},{"created_at":"2018-09-09T11:08:37Z","entry_id":95,"field1":"11271.00","field2":"36.68","field3":"5.14"},{"created_at":"2018-09-09T11:09:49Z","entry_id":96,"field1":"11272.00","field2":"36.69","field3":"5.14"},{"created_at":"2018-09-09T11:11:01Z","entry_id":97,"field1":"11272.00","field2":"36.69","field3":"5.14"},{"created_at":"2018-09-09T11:12:12Z","entry_id":98,"field1":"11273.00","field2":"36.69","field3":"5.14"},{"created_at":"2018-09-09T11:13:24Z","entry_id":99,"field1":"11270.00","field2":"36.68","field3":"5.14"},{"created_at":"2018-09-09T11:14:36Z","entry_id":100,"field1":"11272.00","field2":"36.67","field3":"5.14"},{"created_at":"2018-09-09T11:15:47Z","entry_id":101,"field1":"11272.00","field2":"36.68","field3":"5.14"},{"created_at":"2018-09-09T11:16:59Z","entry_id":102,"field1":"11269.00","field2":"36.69","field3":"5.14"},{"created_at":"2018-09-09T11:18:11Z","entry_id":103,"field1":"11269.00","field2":"36.69","field3":"5.14"},{"created_at":"2018-09-09T14:38:57Z","entry_id":104,"field1":"8720.00","field2":"41.38","field3":"5.14"},{"created_at":"2018-09-09T14:40:09Z","entry_id":105,"field1":"8721.00","field2":"41.38","field3":"5.12"},{"created_at":"2018-09-09T14:41:21Z","entry_id":106,"field1":"8721.00","field2":"41.42","field3":"5.14"},{"created_at":"2018-09-09T14:42:33Z","entry_id":107,"field1":"8730.00","field2":"41.44","field3":"5.14"},{"created_at":"2018-09-09T14:43:44Z","entry_id":108,"field1":"8725.00","field2":"41.44","field3":"5.14"},{"created_at":"2018-09-09T14:44:56Z","entry_id":109,"field1":"8732.00","field2":"41.46","field3":"5.14"},{"created_at":"2018-09-09T14:46:07Z","entry_id":110,"field1":"8730.00","field2":"41.49","field3":"5.14"},{"created_at":"2018-09-09T14:47:19Z","entry_id":111,"field1":"8729.00","field2":"41.49","field3":"5.14"},{"created_at":"2018-09-09T14:48:31Z","entry_id":112,"field1":"8736.00","field2":"41.49","field3":"5.14"},{"created_at":"2018-09-09T14:49:43Z","entry_id":113,"field1":"8737.00","field2":"41.46","field3":"5.14"},{"created_at":"2018-09-09T14:50:54Z","entry_id":114,"field1":"8736.00","field2":"41.44","field3":"5.14"},{"created_at":"2018-09-09T14:52:06Z","entry_id":115,"field1":"8732.00","field2":"41.42","field3":"5.05"},{"created_at":"2018-09-09T14:53:18Z","entry_id":116,"field1":"8735.00","field2":"41.38","field3":"5.10"},{"created_at":"2018-09-09T14:54:30Z","entry_id":117,"field1":"8732.00","field2":"41.38","field3":"5.10"},{"created_at":"2018-09-09T14:55:41Z","entry_id":118,"field1":"8731.00","field2":"41.36","field3":"5.12"},{"created_at":"2018-09-09T14:56:53Z","entry_id":119,"field1":"8743.00","field2":"41.31","field3":"5.12"},{"created_at":"2018-09-09T14:58:04Z","entry_id":120,"field1":"8738.00","field2":"41.25","field3":"5.12"},{"created_at":"2018-09-09T14:59:16Z","entry_id":121,"field1":"8736.00","field2":"41.24","field3":"5.12"},{"created_at":"2018-09-09T15:00:28Z","entry_id":122,"field1":"8738.00","field2":"41.19","field3":"5.12"},{"created_at":"2018-09-09T15:01:40Z","entry_id":123,"field1":"8778.00","field2":"41.16","field3":"5.12"},{"created_at":"2018-09-09T15:02:51Z","entry_id":124,"field1":"8770.00","field2":"41.13","field3":"5.12"},{"created_at":"2018-09-09T15:04:03Z","entry_id":125,"field1":"8772.00","field2":"41.13","field3":"5.12"},{"created_at":"2018-09-09T15:05:15Z","entry_id":126,"field1":"8763.00","field2":"41.19","field3":"5.14"},{"created_at":"2018-09-09T15:06:26Z","entry_id":127,"field1":"8763.00","field2":"41.25","field3":"5.14"},{"created_at":"2018-09-09T15:07:38Z","entry_id":128,"field1":"8772.00","field2":"41.33","field3":"5.14"},{"created_at":"2018-09-12T13:33:26Z","entry_id":129,"field1":"18727.00","field2":"23.02","field3":"4.83"},{"created_at":"2018-09-12T13:34:37Z","entry_id":130,"field1":"18730.00","field2":"23.00","field3":"5.07"},{"created_at":"2018-09-12T13:35:49Z","entry_id":131,"field1":"18738.00","field2":"22.88","field3":"5.10"},{"created_at":"2018-09-12T13:37:01Z","entry_id":132,"field1":"8923.00","field2":"22.94","field3":"5.10"},{"created_at":"2018-09-12T13:38:12Z","entry_id":133,"field1":"18747.00","field2":"22.94","field3":"5.07"},{"created_at":"2018-09-12T13:39:24Z","entry_id":134,"field1":"18527.00","field2":"22.94","field3":"5.07"},{"created_at":"2018-09-12T13:40:36Z","entry_id":135,"field1":"8918.00","field2":"22.95","field3":"5.10"},{"created_at":"2018-09-12T13:41:47Z","entry_id":136,"field1":"18764.00","field2":"23.00","field3":"5.07"},{"created_at":"2018-09-12T13:42:59Z","entry_id":137,"field1":"18753.00","field2":"23.00","field3":"5.10"}]}