{"channel":{"id":571216,"name":"esp8266","latitude":"0.0","longitude":"0.0","field1":"Uptime","field2":"load","field3":"temp","field4":"hum","field5":"press","created_at":"2018-09-07T12:33:28Z","updated_at":"2018-09-09T13:10:03Z","last_entry_id":6374},"feeds":[{"created_at":"2018-09-14T19:32:54Z","entry_id":6275,"field1":null,"field2":"19","field3":null,"field4":null,"field5":null},{"created_at":"2018-09-14T19:33:40Z","entry_id":6276,"field1":null,"field2":null,"field3":"25.2","field4":"49.6","field5":"1018.2"},{"created_at":"2018-09-14T19:37:54Z","entry_id":6277,"field1":null,"field2":"19","field3":null,"field4":null,"field5":null},{"created_at":"2018-09-14T19:38:41Z","entry_id":6278,"field1":null,"field2":null,"field3":"25.3","field4":"49.3","field5":"1018.2"},{"created_at":"2018-09-14T19:42:54Z","entry_id":6279,"field1":null,"field2":"19","field3":null,"field4":null,"field5":null},{"created_at":"2018-09-14T19:43:42Z","entry_id":6280,"field1":null,"field2":null,"field3":"25.3","field4":"49.5","field5":"1018.2"},{"created_at":"2018-09-14T19:47:54Z","entry_id":6281,"field1":null,"field2":"19","field3":null,"field4":null,"field5":null},{"created_at":"2018-09-14T19:48:43Z","entry_id":6282,"field1":null,"field2":null,"field3":"25.3","field4":"49.8","field5":"1018.2"},{"created_at":"2018-09-14T19:52:54Z","entry_id":6283,"field1":null,"field2":"19","field3":null,"field4":null,"field5":null},{"created_at":"2018-09-14T19:53:44Z","entry_id":6284,"field1":null,"field2":null,"field3":"25.2","field4":"49.4","field5":"1018.2"},{"created_at":"2018-09-14T19:57:54Z","entry_id":6285,"field1":null,"field2":"19","field3":null,"field4":null,"field5":null},{"created_at":"2018-09-14T19:58:46Z","entry_id":6286,"field1":null,"field2":null,"field3":"25.2","field4":"49.4","field5":"1018.2"},{"created_at":"2018-09-14T20:02:54Z","entry_id":6287,"field1":null,"field2":"19","field3":null,"field4":null,"field5":null},{"created_at":"2018-09-14T20:03:47Z","entry_id":6288,"field1":null,"field2":null,"field3":"25.2","field4":"49.4","field5":"1018.3"},{"created_at":"2018-09-14T20:07:54Z","entry_id":6289,"field1":null,"field2":"19","field3":null,"field4":null,"field5":null},{"created_at":"2018-09-14T20:08:48Z","entry_id":6290,"field1":null,"field2":null,"field3":"25.1","field4":"49.4","field5":"1018.3"},{"created_at":"2018-09-14T20:12:54Z","entry_id":6291,"field1":null,"field2":"19","field3":null,"field4":null,"field5":null},{"created_at":"2018-09-14T20:13:49Z","entry_id":6292,"field1":null,"field2":null,"field3":"25.1","field4":"49.3","field5":"1018.4"},{"created_at":"2018-09-14T20:17:54Z","entry_id":6293,"field1":null,"field2":"19","field3":null,"field4":null,"field5":null},{"created_at":"2018-09-14T20:18:50Z","entry_id":6294,"field1":null,"field2":null,"field3":"25.1","field4":"49.4","field5":"1018.3"},{"created_at":"2018-09-14T20:22:54Z","entry_id":6295,"field1":null,"field2":"19","field3":null,"field4":null,"field5":null},{"created_at":"2018-09-14T20:23:51Z","entry_id":6296,"field1":null,"field2":null,"field3":"25.0","field4":"49.5","field5":"1018.3"},{"created_at":"2018-09-14T20:27:54Z","entry_id":6297,"field1":null,"field2":"19","field3":null,"field4":null,"field5":null},{"created_at":"2018-09-14T20:28:53Z","entry_id":6298,"field1":null,"field2":null,"field3":"25.0","field4":"49.9","field5":"1018.3"},{"created_at":"2018-09-14T20:32:54Z","entry_id":6299,"field1":null,"field2":"19","field3":null,"field4":null,"field5":null},{"created_at":"2018-09-14T20:33:55Z","entry_id":6300,"field1":null,"field2":null,"field3":"25.0","field4":"49.6","field5":"1018.3"},{"created_at":"2018-09-14T20:37:54Z","entry_id":6301,"field1":null,"field2":"19","field3":null,"field4":null,"field5":null},{"created_at":"2018-09-14T20:38:56Z","entry_id":6302,"field1":null,"field2":null,"field3":"25.0","field4":"49.4","field5":"1018.3"},{"created_at":"2018-09-14T20:42:54Z","entry_id":6303,"field1":null,"field2":"19","field3":null,"field4":null,"field5":null},{"created_at":"2018-09-14T20:43:57Z","entry_id":6304,"field1":null,"field2":null,"field3":"25.0","field4":"49.4","field5":"1018.2"},{"created_at":"2018-09-14T20:47:54Z","entry_id":6305,"field1":null,"field2":"19","field3":null,"field4":null,"field5":null},{"created_at":"2018-09-14T20:48:58Z","entry_id":6306,"field1":null,"field2":null,"field3":"24.9","field4":"49.6","field5":"1018.3"},{"created_at":"2018-09-14T20:52:54Z","entry_id":6307,"field1":null,"field2":"19","field3":null,"field4":null,"field5":null},{"created_at":"2018-09-14T20:53:59Z","entry_id":6308,"field1":null,"field2":null,"field3":"25.0","field4":"49.7","field5":"1018.3"},{"created_at":"2018-09-14T20:57:54Z","entry_id":6309,"field1":null,"field2":"19","field3":null,"field4":null,"field5":null},{"created_at":"2018-09-14T20:59:01Z","entry_id":6310,"field1":null,"field2":null,"field3":"25.0","field4":"50.7","field5":"1018.3"},{"created_at":"2018-09-14T21:02:54Z","entry_id":6311,"field1":null,"field2":"19","field3":null,"field4":null,"field5":null},{"created_at":"2018-09-14T21:04:03Z","entry_id":6312,"field1":null,"field2":null,"field3":"25.0","field4":"50.6","field5":"1018.3"},{"created_at":"2018-09-14T21:07:54Z","entry_id":6313,"field1":null,"field2":"19","field3":null,"field4":null,"field5":null},{"created_at":"2018-09-14T21:09:05Z","entry_id":6314,"field1":null,"field2":null,"field3":"25.1","field4":"50.4","field5":"1018.3"},{"created_at":"2018-09-14T21:12:54Z","entry_id":6315,"field1":null,"field2":"19","field3":null,"field4":null,"field5":null},{"created_at":"2018-09-14T21:14:06Z","entry_id":6316,"field1":null,"field2":null,"field3":"25.1","field4":"50.3","field5":"1018.2"},{"created_at":"2018-09-14T21:17:54Z","entry_id":6317,"field1":null,"field2":"19","field3":null,"field4":null,"field5":null},{"created_at":"2018-09-14T21:19:07Z","entry_id":6318,"field1":null,"field2":null,"field3":"25.1","field4":"50.3","field5":"1018.2"},{"created_at":"2018-09-14T21:22:54Z","entry_id":6319,"field1":null,"field2":"19","field3":null,"field4":null,"field5":null},{"created_at":"2018-09-14T21:24:08Z","entry_id":6320,"field1":null,"field2":null,"field3":"25.1","field4":"50.3","field5":"1018.3"},{"created_at":"2018-09-14T21:27:54Z","entry_id":6321,"field1":null,"field2":"19","field3":null,"field4":null,"field5":null},{"created_at":"2018-09-14T21:29:09Z","entry_id":6322,"field1":null,"field2":null,"field3":"25.1","field4":"50.2","field5":"1018.2"},{"created_at":"2018-09-14T21:32:54Z","entry_id":6323,"field1":null,"field2":"19","field3":null,"field4":null,"field5":null},{"created_at":"2018-09-14T21:34:10Z","entry_id":6324,"field1":null,"field2":null,"field3":"25.0","field4":"50.3","field5":"1018.3"},{"created_at":"2018-09-14T21:37:54Z","entry_id":6325,"field1":null,"field2":"19","field3":null,"field4":null,"field5":null},{"created_at":"2018-09-14T21:39:11Z","entry_id":6326,"field1":null,"field2":null,"field3":"25.0","field4":"50.4","field5":"1018.3"},{"created_at":"2018-09-14T21:42:54Z","entry_id":6327,"field1":null,"field2":"19","field3":null,"field4":null,"field5":null},{"created_at":"2018-09-14T21:44:12Z","entry_id":6328,"field1":null,"field2":null,"field3":"24.9","field4":"50.4","field5":"1018.2"},{"created_at":"2018-09-14T21:47:55Z","entry_id":6329,"field1":null,"field2":"19","field3":null,"field4":null,"field5":null},{"created_at":"2018-09-14T21:49:13Z","entry_id":6330,"field1":null,"field2":null,"field3":"24.9","field4":"50.3","field5":"1018.3"},{"created_at":"2018-09-14T21:52:54Z","entry_id":6331,"field1":null,"field2":"19","field3":null,"field4":null,"field5":null},{"created_at":"2018-09-14T21:54:14Z","entry_id":6332,"field1":null,"field2":null,"field3":"24.9","field4":"50.3","field5":"1018.4"},{"created_at":"2018-09-14T21:57:54Z","entry_id":6333,"field1":null,"field2":"19","field3":null,"field4":null,"field5":null},{"created_at":"2018-09-14T21:59:15Z","entry_id":6334,"field1":null,"field2":null,"field3":"25.0","field4":"49.9","field5":"1018.4"},{"created_at":"2018-09-14T22:02:54Z","entry_id":6335,"field1":null,"field2":"19","field3":null,"field4":null,"field5":null},{"created_at":"2018-09-14T22:04:16Z","entry_id":6336,"field1":null,"field2":null,"field3":"24.9","field4":"50.2","field5":"1018.4"},{"created_at":"2018-09-14T22:07:54Z","entry_id":6337,"field1":null,"field2":"19","field3":null,"field4":null,"field5":null},{"created_at":"2018-09-14T22:09:17Z","entry_id":6338,"field1":null,"field2":null,"field3":"24.8","field4":"50.2","field5":"1018.4"},{"created_at":"2018-09-14T22:12:54Z","entry_id":6339,"field1":null,"field2":"19","field3":null,"field4":null,"field5":null},{"created_at":"2018-09-14T22:14:18Z","entry_id":6340,"field1":null,"field2":null,"field3":"24.9","field4":"49.9","field5":"1018.4"},{"created_at":"2018-09-14T22:17:54Z","entry_id":6341,"field1":null,"field2":"19","field3":null,"field4":null,"field5":null},{"created_at":"2018-09-14T22:19:20Z","entry_id":6342,"field1":null,"field2":null,"field3":"24.9","field4":"49.8","field5":"1018.5"},{"created_at":"2018-09-14T22:22:54Z","entry_id":6343,"field1":null,"field2":"19","field3":null,"field4":null,"field5":null},{"created_at":"2018-09-14T22:24:21Z","entry_id":6344,"field1":null,"field2":null,"field3":"24.8","field4":"49.9","field5":"1018.5"},{"created_at":"2018-09-14T22:27:54Z","entry_id":6345,"field1":null,"field2":"19","field3":null,"field4":null,"field5":null},{"created_at":"2018-09-14T22:29:22Z","entry_id":6346,"field1":null,"field2":null,"field3":"24.8","field4":"49.9","field5":"1018.5"},{"created_at":"2018-09-14T22:32:54Z","entry_id":6347,"field1":null,"field2":"19","field3":null,"field4":null,"field5":null},{"created_at":"2018-09-14T22:34:23Z","entry_id":6348,"field1":null,"field2":null,"field3":"24.8","field4":"49.8","field5":"1018.5"},{"created_at":"2018-09-14T22:37:54Z","entry_id":6349,"field1":null,"field2":"19","field3":null,"field4":null,"field5":null},{"created_at":"2018-09-14T22:39:25Z","entry_id":6350,"field1":null,"field2":null,"field3":"24.8","field4":"49.8","field5":"1018.5"},{"created_at":"2018-09-14T22:42:54Z","entry_id":6351,"field1":null,"field2":"19","field3":null,"field4":null,"field5":null},{"created_at":"2018-09-14T22:44:26Z","entry_id":6352,"field1":null,"field2":null,"field3":"24.7","field4":"49.9","field5":"1018.6"},{"created_at":"2018-09-14T22:47:54Z","entry_id":6353,"field1":null,"field2":"19","field3":null,"field4":null,"field5":null},{"created_at":"2018-09-14T22:49:26Z","entry_id":6354,"field1":null,"field2":null,"field3":"24.7","field4":"49.9","field5":"1018.6"},{"created_at":"2018-09-14T22:52:54Z","entry_id":6355,"field1":null,"field2":"19","field3":null,"field4":null,"field5":null},{"created_at":"2018-09-14T22:54:28Z","entry_id":6356,"field1":null,"field2":null,"field3":"24.7","field4":"49.8","field5":"1018.7"},{"created_at":"2018-09-14T22:57:54Z","entry_id":6357,"field1":null,"field2":"19","field3":null,"field4":null,"field5":null},{"created_at":"2018-09-14T22:59:29Z","entry_id":6358,"field1":null,"field2":null,"field3":"24.7","field4":"49.8","field5":"1018.7"},{"created_at":"2018-09-14T23:02:54Z","entry_id":6359,"field1":null,"field2":"19","field3":null,"field4":null,"field5":null},{"created_at":"2018-09-14T23:04:30Z","entry_id":6360,"field1":null,"field2":null,"field3":"24.6","field4":"49.8","field5":"1018.7"},{"created_at":"2018-09-14T23:07:54Z","entry_id":6361,"field1":null,"field2":"19","field3":null,"field4":null,"field5":null},{"created_at":"2018-09-14T23:09:32Z","entry_id":6362,"field1":null,"field2":null,"field3":"24.6","field4":"49.7","field5":"1018.7"},{"created_at":"2018-09-14T23:12:54Z","entry_id":6363,"field1":null,"field2":"19","field3":null,"field4":null,"field5":null},{"created_at":"2018-09-14T23:14:33Z","entry_id":6364,"field1":null,"field2":null,"field3":"24.6","field4":"49.7","field5":"1018.7"},{"created_at":"2018-09-14T23:17:54Z","entry_id":6365,"field1":null,"field2":"19","field3":null,"field4":null,"field5":null},{"created_at":"2018-09-14T23:19:35Z","entry_id":6366,"field1":null,"field2":null,"field3":"24.6","field4":"49.7","field5":"1018.8"},{"created_at":"2018-09-14T23:22:54Z","entry_id":6367,"field1":null,"field2":"19","field3":null,"field4":null,"field5":null},{"created_at":"2018-09-14T23:24:36Z","entry_id":6368,"field1":null,"field2":null,"field3":"24.6","field4":"49.6","field5":"1018.7"},{"created_at":"2018-09-14T23:27:54Z","entry_id":6369,"field1":null,"field2":"19","field3":null,"field4":null,"field5":null},{"created_at":"2018-09-14T23:29:37Z","entry_id":6370,"field1":null,"field2":null,"field3":"24.6","field4":"49.7","field5":"1018.8"},{"created_at":"2018-09-14T23:32:54Z","entry_id":6371,"field1":null,"field2":"19","field3":null,"field4":null,"field5":null},{"created_at":"2018-09-14T23:34:39Z","entry_id":6372,"field1":null,"field2":null,"field3":"24.6","field4":"49.6","field5":"1018.7"},{"created_at":"2018-09-14T23:37:54Z","entry_id":6373,"field1":null,"field2":"19","field3":null,"field4":null,"field5":null},{"created_at":"2018-09-14T23:39:40Z","entry_id":6374,"field1":null,"field2":null,"field3":"24.5","field4":"49.6","field5":"1018.8"}]}