{"channel":{"id":572645,"name":"Water Level","description":"Water tank level","latitude":"0.0","longitude":"0.0","field1":"level","created_at":"2018-09-09T17:17:14Z","updated_at":"2018-09-10T11:34:49Z","last_entry_id":3188},"feeds":[{"created_at":"2018-09-14T14:53:26Z","entry_id":3089,"field1":"5015"},{"created_at":"2018-09-14T14:59:55Z","entry_id":3090,"field1":"5013"},{"created_at":"2018-09-14T15:06:23Z","entry_id":3091,"field1":"5176"},{"created_at":"2018-09-14T15:09:30Z","entry_id":3092,"field1":"5175"},{"created_at":"2018-09-14T15:12:32Z","entry_id":3093,"field1":"5175"},{"created_at":"2018-09-14T15:18:44Z","entry_id":3094,"field1":"5175"},{"created_at":"2018-09-14T15:34:47Z","entry_id":3095,"field1":"5174"},{"created_at":"2018-09-14T15:38:05Z","entry_id":3096,"field1":"5172"},{"created_at":"2018-09-14T15:41:07Z","entry_id":3097,"field1":"5172"},{"created_at":"2018-09-14T15:44:08Z","entry_id":3098,"field1":"5172"},{"created_at":"2018-09-14T15:50:21Z","entry_id":3099,"field1":"5172"},{"created_at":"2018-09-14T15:53:23Z","entry_id":3100,"field1":"5171"},{"created_at":"2018-09-14T15:56:25Z","entry_id":3101,"field1":"5171"},{"created_at":"2018-09-14T16:05:55Z","entry_id":3102,"field1":"4274"},{"created_at":"2018-09-14T16:12:07Z","entry_id":3103,"field1":"5170"},{"created_at":"2018-09-14T16:21:46Z","entry_id":3104,"field1":"5169"},{"created_at":"2018-09-14T16:28:00Z","entry_id":3105,"field1":"5170"},{"created_at":"2018-09-14T16:31:02Z","entry_id":3106,"field1":"5169"},{"created_at":"2018-09-14T16:37:31Z","entry_id":3107,"field1":"5169"},{"created_at":"2018-09-14T16:40:33Z","entry_id":3108,"field1":"5169"},{"created_at":"2018-09-14T16:49:52Z","entry_id":3109,"field1":"3560"},{"created_at":"2018-09-14T16:52:54Z","entry_id":3110,"field1":"4989"},{"created_at":"2018-09-14T16:56:12Z","entry_id":3111,"field1":"4988"},{"created_at":"2018-09-14T16:59:15Z","entry_id":3112,"field1":"4981"},{"created_at":"2018-09-14T17:05:28Z","entry_id":3113,"field1":"4979"},{"created_at":"2018-09-14T17:08:30Z","entry_id":3114,"field1":"4978"},{"created_at":"2018-09-14T17:14:37Z","entry_id":3115,"field1":"4977"},{"created_at":"2018-09-14T17:17:45Z","entry_id":3116,"field1":"5068"},{"created_at":"2018-09-14T17:20:47Z","entry_id":3117,"field1":"5068"},{"created_at":"2018-09-14T17:27:01Z","entry_id":3118,"field1":"5067"},{"created_at":"2018-09-14T17:30:03Z","entry_id":3119,"field1":"5067"},{"created_at":"2018-09-14T17:36:16Z","entry_id":3120,"field1":"5067"},{"created_at":"2018-09-14T17:42:29Z","entry_id":3121,"field1":"5066"},{"created_at":"2018-09-14T17:45:31Z","entry_id":3122,"field1":"5065"},{"created_at":"2018-09-14T17:48:38Z","entry_id":3123,"field1":"5065"},{"created_at":"2018-09-14T17:51:41Z","entry_id":3124,"field1":"5065"},{"created_at":"2018-09-14T17:57:55Z","entry_id":3125,"field1":"5065"},{"created_at":"2018-09-14T18:04:04Z","entry_id":3126,"field1":"5065"},{"created_at":"2018-09-14T18:07:21Z","entry_id":3127,"field1":"5064"},{"created_at":"2018-09-14T18:10:24Z","entry_id":3128,"field1":"5064"},{"created_at":"2018-09-14T18:29:27Z","entry_id":3129,"field1":"5064"},{"created_at":"2018-09-14T18:32:29Z","entry_id":3130,"field1":"5157"},{"created_at":"2018-09-14T18:42:09Z","entry_id":3131,"field1":"5191"},{"created_at":"2018-09-14T18:45:10Z","entry_id":3132,"field1":"5191"},{"created_at":"2018-09-14T18:54:50Z","entry_id":3133,"field1":"5015"},{"created_at":"2018-09-14T19:04:07Z","entry_id":3134,"field1":"5004"},{"created_at":"2018-09-14T19:07:07Z","entry_id":3135,"field1":"5004"},{"created_at":"2018-09-14T19:13:22Z","entry_id":3136,"field1":"5101"},{"created_at":"2018-09-14T19:22:46Z","entry_id":3137,"field1":"5099"},{"created_at":"2018-09-14T19:25:47Z","entry_id":3138,"field1":"5100"},{"created_at":"2018-09-14T19:28:51Z","entry_id":3139,"field1":"5099"},{"created_at":"2018-09-14T19:31:52Z","entry_id":3140,"field1":"5099"},{"created_at":"2018-09-14T19:34:55Z","entry_id":3141,"field1":"5098"},{"created_at":"2018-09-14T19:38:13Z","entry_id":3142,"field1":"5124"},{"created_at":"2018-09-14T19:41:15Z","entry_id":3143,"field1":"5098"},{"created_at":"2018-09-14T19:44:17Z","entry_id":3144,"field1":"5097"},{"created_at":"2018-09-14T19:50:30Z","entry_id":3145,"field1":"5097"},{"created_at":"2018-09-14T19:53:32Z","entry_id":3146,"field1":"5096"},{"created_at":"2018-09-14T19:59:40Z","entry_id":3147,"field1":"5096"},{"created_at":"2018-09-14T20:08:58Z","entry_id":3148,"field1":"5096"},{"created_at":"2018-09-14T20:12:00Z","entry_id":3149,"field1":"5096"},{"created_at":"2018-09-14T20:15:17Z","entry_id":3150,"field1":"5095"},{"created_at":"2018-09-14T20:21:45Z","entry_id":3151,"field1":"5096"},{"created_at":"2018-09-14T20:24:47Z","entry_id":3152,"field1":"5095"},{"created_at":"2018-09-14T20:31:00Z","entry_id":3153,"field1":"5095"},{"created_at":"2018-09-14T20:43:41Z","entry_id":3154,"field1":"5095"},{"created_at":"2018-09-14T20:46:44Z","entry_id":3155,"field1":"5045"},{"created_at":"2018-09-14T20:52:58Z","entry_id":3156,"field1":"5094"},{"created_at":"2018-09-14T20:56:15Z","entry_id":3157,"field1":"4948"},{"created_at":"2018-09-14T21:02:28Z","entry_id":3158,"field1":"5062"},{"created_at":"2018-09-14T21:05:31Z","entry_id":3159,"field1":"5060"},{"created_at":"2018-09-14T21:11:45Z","entry_id":3160,"field1":"5060"},{"created_at":"2018-09-14T21:17:58Z","entry_id":3161,"field1":"5058"},{"created_at":"2018-09-14T21:27:17Z","entry_id":3162,"field1":"5056"},{"created_at":"2018-09-14T21:30:19Z","entry_id":3163,"field1":"5056"},{"created_at":"2018-09-14T21:39:58Z","entry_id":3164,"field1":"5056"},{"created_at":"2018-09-14T21:43:00Z","entry_id":3165,"field1":"5055"},{"created_at":"2018-09-14T21:46:02Z","entry_id":3166,"field1":"5205"},{"created_at":"2018-09-14T21:58:48Z","entry_id":3167,"field1":"5204"},{"created_at":"2018-09-14T22:01:50Z","entry_id":3168,"field1":"5204"},{"created_at":"2018-09-14T22:05:07Z","entry_id":3169,"field1":"5204"},{"created_at":"2018-09-14T22:11:19Z","entry_id":3170,"field1":"5292"},{"created_at":"2018-09-14T22:14:21Z","entry_id":3171,"field1":"5292"},{"created_at":"2018-09-14T22:20:35Z","entry_id":3172,"field1":"5291"},{"created_at":"2018-09-14T22:23:38Z","entry_id":3173,"field1":"5359"},{"created_at":"2018-09-14T22:27:00Z","entry_id":3174,"field1":"5455"},{"created_at":"2018-09-14T22:30:02Z","entry_id":3175,"field1":"5552"},{"created_at":"2018-09-14T22:36:25Z","entry_id":3176,"field1":"5561"},{"created_at":"2018-09-14T22:39:43Z","entry_id":3177,"field1":"5561"},{"created_at":"2018-09-14T22:49:22Z","entry_id":3178,"field1":"5560"},{"created_at":"2018-09-14T22:52:24Z","entry_id":3179,"field1":"5591"},{"created_at":"2018-09-14T23:05:02Z","entry_id":3180,"field1":"5430"},{"created_at":"2018-09-14T23:08:19Z","entry_id":3181,"field1":"5429"},{"created_at":"2018-09-14T23:11:21Z","entry_id":3182,"field1":"5403"},{"created_at":"2018-09-14T23:17:42Z","entry_id":3183,"field1":"5428"},{"created_at":"2018-09-14T23:20:44Z","entry_id":3184,"field1":"5427"},{"created_at":"2018-09-14T23:26:58Z","entry_id":3185,"field1":"5426"},{"created_at":"2018-09-14T23:33:11Z","entry_id":3186,"field1":"5401"},{"created_at":"2018-09-14T23:39:24Z","entry_id":3187,"field1":"5401"},{"created_at":"2018-09-14T23:42:25Z","entry_id":3188,"field1":"5401"}]}